qubayes-0.1.0.dist-info/METADATA
qubayes-0.1.0.dist-info/WHEEL
qubayes-0.1.0.dist-info/entry_points.txt
qubayes-0.1.0.dist-info/licenses/LICENSE.txt
qubayes/__init__.py
qubayes/bayesnet/__init__.py
qubayes/utils.py
qubayes-0.1.0.dist-info/RECORD
