Metadata-Version: 2.1
Name: QuBayes
Version: 0.1.0
Summary: Python package for performing quantum Bayesian inference
Author: Zeji Li, Zi-ming Li
License: Apache-2.0
Requires-Python: >=3.12
